{
  "category": "US History Trivia",
  "questions": [
    {
      "question": "Which document was adopted on July 4, 1776, declaring the United States' independence from Great Britain?",
      "choices": [
        "A) The Bill of Rights",
        "B) The Emancipation Proclamation",
        "C) The Declaration of Independence",
        "D) The Constitution"
      ],
      "correct_choice": "C"
    },
    {
      "question": "Which American Founding Father is known for writing many of the Federalist Papers and being the first Secretary of the Treasury?",
      "choices": [
        "A) Thomas Jefferson",
        "B) George Washington",
        "C) Benjamin Franklin",
        "D) Alexander Hamilton"
      ],
      "correct_choice": "D"
    },
    {
      "question": "During which war did the Battle of Gettysburg take place?",
      "choices": [
        "A) American Revolution",
        "B) Civil War",
        "C) War of 1812",
        "D) World War I"
      ],
      "correct_choice": "B"
    },
    {
      "question": "Which amendment to the US Constitution grants citizenship to all persons born or naturalized in the United States?",
      "choices": [
        "A) 1st Amendment",
        "B) 5th Amendment",
        "C) 14th Amendment",
        "D) 19th Amendment"
      ],
      "correct_choice": "C"
    },
    {
      "question": "What was the main purpose of the Lewis and Clark expedition?",
      "choices": [
        "A) To find a new trade route to Asia",
        "B) To explore and map the newly acquired Louisiana Purchase",
        "C) To establish a settlement in California",
        "D) To search for gold in the Rocky Mountains"
      ],
      "correct_choice": "B"
    },
    {
      "question": "Which president is known for implementing the New Deal in response to the Great Depression?",
      "choices": [
        "A) Franklin D. Roosevelt",
        "B) Herbert Hoover",
        "C) Woodrow Wilson",
        "D) Calvin Coolidge"
      ],
      "correct_choice": "A"
    },
    {
      "question": "The United States purchased the territory of Alaska from which country?",
      "choices": ["A) Russia", "B) Canada", "C) Spain", "D) France"],
      "correct_choice": "A"
    },
    {
      "question": "What event marked the beginning of the Great Depression in the United States?",
      "choices": [
        "A) The stock market crash of 1929",
        "B) The end of World War II",
        "C) The signing of the Declaration of Independence",
        "D) The California Gold Rush"
      ],
      "correct_choice": "A"
    },
    {
      "question": "Which US president issued the Emancipation Proclamation, declaring slaves in Confederate states to be free?",
      "choices": [
        "A) Abraham Lincoln",
        "B) Andrew Johnson",
        "C) Ulysses S. Grant",
        "D) James Buchanan"
      ],
      "correct_choice": "A"
    },
    {
      "question": "What was the name of the ship that transported the Pilgrims to the New World in 1620?",
      "choices": [
        "A) Mayflower",
        "B) Santa Maria",
        "C) Nina",
        "D) Golden Hind"
      ],
      "correct_choice": "A"
    }
  ]
}
